{
    "name": "快速直达专线37",
    "from_stop_zh": "中关村南",
    "from_stop_pinyin": "ZHONGGUANCUNNAN",
    "to_stop_zh": "昌平东关",
    "to_stop_pinyin": "CHANGPINGDONGGUAN",
    "schedule": "平日17:50,18:00节假日停驶",
    "fare": "单一票制票价20元刷卡12元各种票证无效",
    "stops": [
        [
            "中关村南",
            1
        ],
        [
            "海淀中街北站",
            2
        ],
        [
            "北京市地震局",
            3
        ],
        [
            "中关村西",
            4
        ],
        [
            "中关村一街",
            5
        ],
        [
            "保福寺桥西",
            6
        ],
        [
            "昌平西关环岛东",
            7
        ],
        [
            "建明里小区",
            8
        ],
        [
            "昌平鼓楼西街",
            9
        ],
        [
            "昌平鼓楼东街",
            10
        ],
        [
            "昌平一中",
            11
        ],
        [
            "松园小区西门",
            12
        ],
        [
            "亢山广场",
            13
        ],
        [
            "昌平东关",
            14
        ]
    ]
}